quadmoments-0.1.0.dist-info/METADATA
quadmoments-0.1.0.dist-info/WHEEL
quadmoments/__init__.py
quadmoments/torch/decompose.py
quadmoments/torch/baseline.py
quadmoments/torch/__init__.py
quadmoments/torch/quadform.py
quadmoments/torch/quadmoments.py
quadmoments/numpy/decompose.py
quadmoments/numpy/baseline.py
quadmoments/numpy/__init__.py
quadmoments/numpy/quadmoments.py
quadmoments/error.py
quadmoments/coefs.cpython-311-x86_64-linux-gnu.so
quadmoments-0.1.0.dist-info/RECORD
