Metadata-Version: 2.1
Name: quadmoments
Version: 0.1.0
Classifier: Programming Language :: Rust
Classifier: Programming Language :: Python :: Implementation :: CPython
Classifier: Programming Language :: Python :: Implementation :: PyPy
Requires-Dist: torch
Requires-Dist: numpy
Requires-Dist: scipy
Requires-Python: >=3.8
